ibm_eventnotifications/__init__.py
ibm_eventnotifications/common.py
ibm_eventnotifications/event_notifications_v1.py
ibm_eventnotifications/version.py
ibm_eventnotifications-0.22.0.dist-info/licenses/LICENSE
ibm_eventnotifications-0.22.0.dist-info/METADATA
ibm_eventnotifications-0.22.0.dist-info/WHEEL
ibm_eventnotifications-0.22.0.dist-info/top_level.txt
ibm_eventnotifications-0.22.0.dist-info/zip-safe
ibm_eventnotifications-0.22.0.dist-info/RECORD
