Metadata-Version: 2.4
Name: ibm-eventnotifications
Version: 0.22.0
Summary: Python server SDK for IBM Cloud Event Notifications service
Home-page: https://github.com/IBM/event-notifications-python-admin-sdk
Author: IBM
Author-email: Notifications-prod@ibm.com
License: Apache 2.0
Keywords: ibm_eventnotifications
Classifier: Programming Language :: Python
Classifier: Programming Language :: Python :: 3
Classifier: Programming Language :: Python :: 3.8
Classifier: Programming Language :: Python :: 3.9
Classifier: Programming Language :: Python :: 3.10
Classifier: Programming Language :: Python :: 3.11
Classifier: Development Status :: 4 - Beta
Classifier: Intended Audience :: Developers
Classifier: License :: OSI Approved :: Apache Software License
Classifier: Operating System :: OS Independent
Classifier: Topic :: Software Development :: Libraries :: Python Modules
Classifier: Topic :: Software Development :: Libraries :: Application Frameworks
License-File: LICENSE
Requires-Dist: ibm_cloud_sdk_core<4.0.0,>=3.20.6
Dynamic: author
Dynamic: author-email
Dynamic: classifier
Dynamic: description
Dynamic: description-content-type
Dynamic: home-page
Dynamic: keywords
Dynamic: license
Dynamic: license-file
Dynamic: requires-dist
Dynamic: summary
